{
  "Talk06": "\u003csp:3:0:2:0901\u003eCome here!",
  "Talk07": "\u003csp:3:0:2:0200\u003e\u003csnd:QuestionNormal\u003eHaven\u0027t you heard?\n\n\nIt\u0027s strictly forbidden to get near that\nRing Ruin, by \u003cclr:0000\u003ePrincess Zelda\u0027s orders\u003cclr:ffff\u003e.\n\nSo you\u0027d better be on your way.",
  "0000": "Princess Zelda\u0027s orders?",
  "Talk03": "\u003csp:3:0:2:0900\u003e\u003csnd:CallFar\u003e\u003csp:0:2:2:7d00\u003eHey! \u003csp:5:0:0\u003eYou there!\u003csp:0:2:2:6400\u003e",
  "0001": "OK.",
  "Talk08": "\u003csp:3:0:2:0700\u003e\u003csnd:TalkPositive_01\u003eYou heard me. \u003csp:5:0:0\u003ePrincess Zelda came out to\nKakariko Village the other day and told\neveryone to steer clear of that Ring Ruin.\n\u003csp:3:0:2:0c00\u003eShe left in a hurry, so I didn\u0027t quite catch\nthe why of it all.\n\n\u003csp:3:0:2:0701\u003eAs you\u0027ve surely noticed, \u003csp:5:0:0\u003ethese ruins\ncould come crumbling down at any time.\n\nSo folks need to keep away so they don\u0027t\nget injured.\u003csp:5:0:0\u003e I\u0027m sure that\u0027s where her\nconcerns were coming from.",
  "Talk09": "\u003csp:3:0:2:0c00\u003e\u003csnd:Sad\u003e\u003csp:0:2:2:5000\u003eI reeeally want to get in there and poke around. \u003csp:5:0:0\u003eBut\nI\u0027d be directly opposing Princess Zelda\u0027s orders...\n\nIs this the end of my dream that someday Princess\nZelda will call me Doctor Calip?\u003csp:0:2:2:6400\u003e"
}