{
  "near0000": "\u003csnd:CallFar\u003eIt\u0027s fresh as can be!",
  "near0001": "\u003csnd:CallFar\u003eIt\u0027s all freshly grilled!",
  "Com_Talk_13": "\u003csp:3:0:2:0000\u003eHow many?",
  "Com_Talk_14": "\u003csp:3:0:2:0000\u003eThat\u0027s \u003csp:2:f:28:2200530068006f0070005f00540072006100640065004900740065006d004e0075006d00ffff00cd\u003e of them, you said? OK, then...\nHow\u0027s \u003cclr:0000\u003e\u003csp:2:12:2c:2600530068006f0070005f00540072006100640065004900740065006d0050007200690063006500ffff00cd\u003e \u003csp:c9:6:1c:0a00720075007000650065000c007200750070006500650073000000\u003e\u003cclr:ffff\u003e sound?",
  "5500": "OK.",
  "Com_Talk_15": "\u003csp:3:0:2:0c00\u003eI don\u0027t... \u003csp:5:0:0\u003eNo, I don\u0027t like that.\nSomething else please!",
  "5501": "Never mind.",
  "Com_Talk_16": "\u003csp:3:0:2:0c00\u003eOh... Are you so in need of rupees that\nyou\u0027re selling the clothes right off your\nback? That\u0027s not quite how I do things.",
  "5503": "Never mind.",
  "Com_Talk_50": "\u003csp:3:0:2:0700\u003eWanna buy that for \u003cclr:0000\u003e\u003csp:2:12:2c:2600530068006f0070005f00540072006100640065004900740065006d0050007200690063006500ffff00cd\u003e \u003csp:c9:6:1c:0a00720075007000650065000c007200750070006500650073000000\u003e\u003cclr:ffff\u003e?",
  "5508": "All of them.",
  "GreetingAfter00": "\u003csp:3:0:2:0700\u003eVotta!\u003csp:5:1:0\u003e Oh, a Hylian...\u003csp:5:0:0\u003e In that case...\n\n\n\u003csp:3:0:2:0c01\u003eGood born...\u003csp:5:0:0\u003e Good norn...\u003csp:5:0:0\u003e No, that\u0027s not\nit. \u003csp:5:1:0\u003eUmmm...\n\n\u003csp:3:0:2:0800\u003e\u003csnd:Greeting\u003eMorneg!\u003csp:5:1:0\u003e Good morneg! That\u0027s it, right?!",
  "Com_Talk_53": "\u003csp:3:0:2:0100\u003e\u003csnd:LaughS\u003eHey! Is this some kind of haggling\ntechnique?\u003csp:5:0:0\u003e You know being short and\nsuccinct is all the rage now, right?",
  "GreetingAfter01": "\u003csp:3:0:2:0700\u003eSav\u0027a!\u003csp:5:1:0\u003e Oh, a Hylian...\u003csp:5:0:0\u003e In that case...",
  "GreetingAfter02": "\u003csp:3:0:2:0c01\u003eNeh...\u003csp:5:0:0\u003e Mih...\u003csp:5:0:0\u003e No, that\u0027s not right...\u003csp:5:1:0\u003e\nHmmm...\u003csp:5:1:0\u003e Oh!\u003csp:5:1:0\u003e\n\n\u003csp:3:0:2:0800\u003e\u003csnd:Greeting\u003eHel-eye! That\u0027s it, right?!",
  "Com_Talk_55": "\u003csp:3:0:2:0b00\u003eWhoa, hold on! You can\u0027t just cram meat\nof this quality into an already-overloaded\npouch! Make some space first!",
  "GreetingAfter03": "\u003csp:3:0:2:0c00\u003eLet\u0027s see... Vasaaq was...bell...\u003csp:5:0:0\u003e Cell...\u003csp:5:0:0\u003e Oh!\u003csp:5:1:0\u003e\n\n\n\u003csp:3:0:2:0801\u003eDellcam! That\u0027s it, right?!",
  "0000": "Buy from me?",
  "Com_Talk_02b": "\u003csp:3:0:2:0800\u003eTank you!",
  "GreetingAfter04": "\u003csp:3:0:2:0c01\u003eGood oven...\u003csp:5:0:0\u003e Good ivan...\u003csp:5:0:0\u003e No, that\u0027s not\nright...\u003csp:5:1:0\u003e Hmmm...\u003csp:5:1:0\u003e Oh!\u003csp:5:1:0\u003e\n\n\u003csp:3:0:2:0800\u003e\u003csnd:Greeting\u003eGood eveny! That\u0027s it, right?!",
  "0001": "New kind of creature?",
  "Com_Talk_02c": "\u003csp:3:0:2:0800\u003eA-preach-e-ated!",
  "Com_Talk_05b": "\u003csp:3:0:2:0100\u003eKeep it coming!",
  "talk0000": "\u003csp:3:0:2:0a00\u003eI traveled the world a long time ago—\nthat\u0027s how I learned so much about the\ndifferences between our languages.\nThe Upheaval has put a stop to that,\nthough. I can feel my encyclopedic\nknowledge of language slipping away...\n\u003csp:3:0:2:0100\u003e\u003csnd:Happy\u003eBut hey, the sand shroud cleared up.\nMaybe the Upheaval will follow suit!\n\nI hope that\u0027s the case. I heard a \u003cclr:0000\u003enew kind\nof creature\u003cclr:ffff\u003e was recently discovered, and\nI\u0027d love to see it.",
  "0002": "Sav\u0027orq!",
  "Com_Talk_00": "\u003csp:3:0:2:0700\u003eGreat! Show me what you\u0027d like to sell!",
  "Com_Talk_02d": "\u003csp:3:0:2:0800\u003eSarq!",
  "Com_Talk_05c": "\u003csp:3:0:2:0100\u003eI\u0027ll buy more and more!",
  "talk0001": "\u003csp:3:0:2:0100\u003e\u003csnd:Happy\u003eThe sand shroud cleared up eventually,\nso I bet the Upheaval will sort itself\nout too!\nI hope that\u0027s the case. I heard a \u003cclr:0000\u003enew kind\nof creature\u003cclr:ffff\u003e was recently discovered, and\nI\u0027d love to see it.",
  "Com_Talk_01": "\u003csp:3:0:2:0000\u003eHow\u0027s \u003cclr:0000\u003e\u003csp:2:12:2c:2600530068006f0070005f00540072006100640065004900740065006d0050007200690063006500ffff00cd\u003e \u003csp:c9:6:1c:0a00720075007000650065000c007200750070006500650073000000\u003e\u003cclr:ffff\u003e sound? Do we\nhave a deal?",
  "Com_Talk_05d": "\u003csp:3:0:2:0100\u003eAre you sure there isn\u0027t anything else\nyou\u0027d like to sell? Come on, show me!",
  "talk0002": "\u003csp:3:0:2:0000\u003eBefore the Upheaval happened, a traveler\nmentioned it to me...\n\nA new kind of creature was discovered in\n\u003cclr:0000\u003eFaron\u003cclr:ffff\u003e. I heard they\u0027re keeping some at\n\u003cclr:0000\u003eLakeside Stable\u003cclr:ffff\u003e!\n\u003csp:3:0:2:0100\u003e\u003csnd:LaughS\u003eIf you wanted to get to Faron from here,\nyou\u0027d just have to head east and keep\ngoing.\u003csp:5:1:0\u003e And going. \u003csp:5:1:0\u003eAnd going.\u003csp:5:1:0\u003e\nA new creature... Pretty good reason to\ntravel there, yeah?\n\nI wouldn\u0027t hunt it, of course! To kill a\nbrand-new discovery without a second\nthought... \u003csp:5:1:0\u003eNo way.\n\u003csp:3:0:2:0800\u003e\u003csnd:LaughS\u003eBut as something of a hunter, I\u0027d need to\nsee this new meat with my own eyes!\n\n\u003csp:3:0:2:0400\u003eEr, did I say meat? \u003csp:5:1:0\u003eI meant creature.",
  "Talk_33": "\u003csp:3:0:2:0c00\u003eUmmm... Sarq was... It started with a T,\nright?\u003csp:5:0:0\u003e T... \u003csp:5:0:0\u003eOh!\u003csp:5:1:0\u003e\n\n\u003csp:3:0:2:0800\u003eTank you! Tank you berry such!\nThat\u0027s it, right?",
  "Com_Talk_02": "\u003csp:3:0:2:0800\u003eTank you!\u003csp:5:0:0\u003e",
  "talk0003": "\u003csp:3:0:2:0b00\u003e\u003csnd:Happy\u003eOh wow! You\u0027ve got that pronunciation\ndown! What was it in your language...\n\n\u003csp:3:0:2:0100\u003eGoooooo-eye!",
  "Talk_34": "\u003csp:3:0:2:0801\u003e\u003csnd:LaughS\u003eSarq!\n\n\nIf this keeps up, the only thing stopping\nme from traveling will be the Upheaval!",
  "talk0004": "\u003csp:3:0:2:0100\u003e\u003csnd:Happy\u003eKeep buying my stock! The more you buy,\nthe closer I get to traveling again!",
  "Talk_35": "\u003csp:3:0:2:0101\u003e\u003csnd:LaughS\u003eI\u0027ll grill up some more meat to have ready\nfor you the next time you visit!",
  "Com_Talk_04": "\u003csp:3:0:2:0c00\u003eWhat? You changed your mind?\u003csp:5:0:0\u003e\nWell, OK then...",
  "Com_Talk_33": "\u003csp:3:0:2:0000\u003eJust one, right?\u003csp:5:0:0\u003e Let\u0027s say \u003cclr:0000\u003e\u003csp:2:12:2c:2600530068006f0070005f00540072006100640065004900740065006d0050007200690063006500ffff00cd\u003e \u003csp:c9:6:1c:0a00720075007000650065000c007200750070006500650073000000\u003e\u003cclr:ffff\u003e.\nSound good to you?",
  "talk0005": "\u003csp:3:0:2:0800\u003eI really appreciate you buying up all the\nmeat I had for sale. Really. It means a lot!",
  "Talk_36": "\u003csp:3:0:2:0101\u003e\u003csnd:LaughS\u003eSarq! Looks like I\u0027ve got to go hunt some\nmore, huh?",
  "Com_Talk_05": "\u003csp:3:0:2:0000\u003eYou can always sell lots to me! If you want\nto, that is.",
  "Com_Talk_35": "\u003csp:3:0:2:0000\u003eOh, all \u003csp:2:f:28:2200530068006f0070005f00540072006100640065004900740065006d004e0075006d00ffff00cd\u003e of them? I\u0027ll buy them for\n\u003cclr:0000\u003e\u003csp:2:12:2c:2600530068006f0070005f00540072006100640065004900740065006d0050007200690063006500ffff00cd\u003e \u003csp:c9:6:1c:0a00720075007000650065000c007200750070006500650073000000\u003e\u003cclr:ffff\u003e then, OK?",
  "talk0008": "\u003csp:3:0:2:0100\u003eOne day, I\u0027ll be able to travel. I should\nstart saving now so I can hit the road the\nmoment it\u0027s not so dangerous!",
  "talk0009": "\u003csp:3:0:2:0100\u003eSeeing the things you carry with you...\nIt really sparks my traveler\u0027s spirit! \n\nI want to get out there and see this\n\u003cclr:0000\u003enew kind of creature\u003cclr:ffff\u003e I\u0027ve heard about.",
  "talk0010": "\u003csp:3:0:2:0a00\u003eI haven\u0027t been able to travel in some time.\nI hope I can refresh those memories...\n\n\u003csp:3:0:2:0101\u003eBut hey, the sand shroud cleared up.\nMaybe the Upheaval will follow suit!\n\nI hope that\u0027s the case. I heard a \u003cclr:0000\u003enew kind\nof creature\u003cclr:ffff\u003e was recently discovered, and\nI\u0027d love to see it.",
  "talk0011": "\u003csp:3:0:2:0800\u003eYou\u0027ve cleaned me out! Sarq!\n\n\nEvery sale brings me one step closer to\nbeing able to travel someday..."
}