{
  "Com_Talk_02c": "\u003csp:3:0:2:0100\u003e\u003csnd:LaughL_01\u003eA good transaction is one that satisfies\nboth parties. So...are you satisfied?\nIf you\u0027re still selling, I\u0027m still buying!",
  "5508": "I\u0027ll sell them all.",
  "Com_Talk_02d": "\u003csp:3:0:2:0100\u003e\u003csnd:Happy_00\u003eThanks for coming to me! Anything else\nyou want to sell? I\u0027ll give you a good deal!",
  "Talk1028b": "\u003csp:3:0:2:0000\u003e\u003csnd:Happy\u003eIt won\u0027t warm you up like a \u003cclr:0000\u003ebonfire \u003cclr:ffff\u003ewill,\nbut it\u0027s hard to beat it for size and\nsheer brightness.",
  "Com_Talk_50": "\u003csp:3:0:2:0000\u003e\u003csnd:TalkPositive\u003eOooh, OK!\u003cclr:0000\u003e \u003cclr:ffff\u003eThat\u0027ll be \u003cclr:0000\u003e\u003csp:2:10:2e:2800530068006f0070005f00530065006c006500630074004900740065006d0050007200690063006500ffff0001\u003e rupees\u003cclr:ffff\u003e!",
  "Com_Talk_11": "\u003csp:3:0:2:0100\u003e\u003csnd:Happy_00\u003eRight, then. Thanks for the business!",
  "Talk1028": "\u003csp:3:0:2:0700\u003eHey there. \u003csp:5:0:0\u003eAre you here because you\nspotted the \u003cclr:0000\u003ebonfires\u003cclr:ffff\u003e?\u003csp:0:4:0\u003eThe blizzard makes it hard to see where\nyou\u0027re going, so we keep these bonfires\ngoing as a beacon for lost travelers.\u003csp:0:4:0\u003e\u003csp:3:0:2:0100\u003eThey eat up a lot of firewood, but it\u0027s\nworth it—you can spot them even from\nup in the air!\u003csp:0:4:0\u003e\u003csp:3:0:2:0301\u003eThough as proud as I am of them, they\ncan\u0027t beat the spotlights set up around\nthat fancy \u003cclr:0000\u003eSkyview Tower\u003cclr:ffff\u003e.",
  "Talk1030b": "\u003csp:3:0:2:0001\u003eIt hurts to admit, but I don\u0027t see how our\n\u003cclr:0000\u003ebonfires \u003cclr:ffff\u003ecan compete with that.",
  "Talk1010": "\u003csp:3:0:2:0000\u003e\u003csnd:Greeting\u003eThis is the armor shop \u003cclr:0000\u003eBrazen Beak\u003cclr:ffff\u003e.\nI\u0027m happy to say we\u0027re open for business!",
  "Com_Talk_05b": "\u003csp:3:0:2:0001\u003eFeel free to take your time picking\nthrough your pouch. No pressure.",
  "Com_Talk_53": "\u003csp:3:0:2:0001\u003e\u003csnd:Think\u003eNot buying it after all? That\u0027s a shame.\nWell, feel free to keep looking around.",
  "Talk1029": "\u003csp:3:0:2:0700\u003eIf you lose your way in the blizzard,\nyou can count on our \u003cclr:0000\u003ebonfires \u003cclr:ffff\u003eto help\nget you oriented.",
  "Com_Talk_05c": "\u003csp:3:0:2:0000\u003eI\u0027ll buy basically anything.",
  "Com_Talk_13": "\u003csp:3:0:2:0000\u003eHow many do you want to sell?",
  "Talk1011": "\u003csp:3:0:2:0100\u003e\u003csnd:TalkPositive\u003eThis is the armor shop \u003cclr:0000\u003eBrazen Beak\u003cclr:ffff\u003e.\nI\u0027m happy to say we\u0027re open for business!\u003csp:0:4:0\u003eOur armor is perfect for \u003cclr:0000\u003eprotecting\nyourself against the cold\u003cclr:ffff\u003e.\u003csp:0:4:0\u003eIf you\u0027re heading into the mountains, the\ncold gets pretty biting there. Prepare for\nit now or regret it later!",
  "Talk1029b_01": "\u003csp:3:0:2:0700\u003eIf you lose your way in the blizzard,\nyou can count on our \u003cclr:0000\u003ebonfires \u003cclr:ffff\u003eto help\nget you oriented...",
  "Talk1012": "\u003csp:3:0:2:0001\u003eNow then, was there anything else?",
  "Com_Talk_05d": "\u003csp:3:0:2:0100\u003eGo ahead and sell me whatever. It\u0027s all\nstuff you probably don\u0027t need anyway.",
  "Com_Talk_14": "\u003cclr:0000\u003e\u003csp:3:0:2:0000\u003e\u003cclr:ffff\u003eOK, so \u003csp:2:f:28:2200530068006f0070005f00540072006100640065004900740065006d004e0075006d00ffff00cd\u003e of them...\u003csp:5:0:0\u003e I\u0027ll buy those\nfor \u003cclr:0000\u003e\u003csp:2:12:2c:2600530068006f0070005f00540072006100640065004900740065006d0050007200690063006500ffff00cd\u003e \u003csp:c9:6:1c:0a00720075007000650065000c007200750070006500650073000000\u003e\u003cclr:ffff\u003e!",
  "Com_Talk_55": "\u003csp:3:0:2:0401\u003e\u003csnd:QuestionNormal\u003eAh, the thing is... It looks like your bag\nis full. I\u0027d be happy to buy anything you\ndon\u0027t need off of you.",
  "Talk1029b_02": "\u003csp:3:0:2:0500\u003e\u003csnd:QuestionNormal\u003eAll right, I admit it.\u003csp:5:0:0\u003e\u003csp:0:4:0\u003eOnce that \u003cclr:0000\u003eSkyview Tower\u003cclr:ffff\u003e\u0027s flashy lights\nget going, it\u0027ll make for a way better\nlandmark than my bonfires.\u003csp:5:1:0\u003e",
  "Talk1013": "\u003csp:3:0:2:0001\u003eIs that it for you?",
  "Com_Talk_15": "\u003csp:3:0:2:0300\u003e\u003csnd:Think\u003eSorry to have to tell you this, but...\u003csp:5:1:0\u003e That\u0027s\none of the few things I won\u0027t buy.",
  "Com_Talk_11b": "\u003csp:3:0:2:0100\u003e\u003csnd:LaughS\u003eThanks for your purchase!",
  "Talk1029b_03": "\u003csp:3:0:2:0701\u003eProbably better that you rely on that thing\nonce they switch it on. I know when I\u0027m\nbeing outshone.",
  "Talk1014": "\u003csp:3:0:2:0000\u003e\u003csnd:TalkPositive\u003eI might be sold out now, but I\u0027ll get more\nin soon. Buy as many as you like so you\ncan dye \u0027em up special!",
  "0001": "I\u0027m here to sell.",
  "Com_Talk_16": "\u003csp:3:0:2:0400\u003e\u003csnd:QuestionNormal\u003eWait a minute! I\u0027m not buying anything\nyou\u0027re wearing until you take it off first.",
  "Com_Talk_11c": "\u003csp:3:0:2:0100\u003e\u003csnd:LaughL_01\u003eThanks for being a big spender!",
  "0002": "Goodbye.",
  "Com_Talk_11d": "\u003csp:3:0:2:0000\u003e\u003csnd:LaughS\u003eI must say, that suits you.",
  "Com_Talk_00": "\u003csp:3:0:2:0000\u003e\u003csnd:TalkPositive\u003eAhh, looking to sell? We can do that!\nWhat are you selling?",
  "0003": "What is this place?",
  "near1001": "Armor! Warm clothes!",
  "Com_Talk_01": "\u003csp:3:0:2:0000\u003eThat\u0027ll be \u003cclr:0000\u003e\u003csp:2:12:2c:2600530068006f0070005f00540072006100640065004900740065006d0050007200690063006500ffff00cd\u003e\u003csp:c9:6:20:0c002000720075007000650065000e0020007200750070006500650073000000\u003e\u003cclr:ffff\u003e. Sound good?",
  "Com_Talk_02": "\u003csp:3:0:2:0100\u003e\u003csnd:LaughS\u003eThanks! Anything else you want to\nsell me?",
  "Talk1001": "\u003csp:3:0:2:0400\u003e\u003csnd:SurpriseS\u003eWait, do you already have the whole\nRito getup?\u003csp:5:1:0\u003e Thanks for coming back\nagain and again!\n\u003csp:3:0:2:0100\u003eI appreciate your business!",
  "Talk1028b_01": "\u003csp:3:0:2:0700\u003eHey there. \u003csp:5:0:0\u003eAre you here because you\nspotted the \u003cclr:0000\u003ebonfires\u003cclr:ffff\u003e?\u003csp:0:4:0\u003eThe blizzard makes it hard to see where\nyou\u0027re going, so we keep these bonfires\ngoing as a beacon for lost travelers.\u003csp:0:4:0\u003e\u003csp:3:0:2:0100\u003eThey eat up a lot of firewood, but it\u0027s\nworth it—you can spot them even from\nup in the air!\u003csp:0:4:0\u003e\u003csp:3:0:2:0301\u003eThat said, our \u003cclr:0000\u003ebonfires\u003cclr:ffff\u003e might not always\nbe the brightest thing around.\u003csp:5:0:0\u003e\u003csp:0:4:0\u003eHave you seen what they built over there?",
  "Talk1002": "\u003csp:3:0:2:0000\u003e\u003csnd:TalkPositive\u003eYou know, a stylish customer passing\nthrough told me there\u0027s someplace out\nthere that can \u003cclr:0000\u003edye \u003cclr:ffff\u003eclothing.\u003csp:0:4:0\u003eIf you buy extra sets and dye them each\ndifferent colors, you can wear whatever\noutfits suit you on a given day!\u003csp:0:4:0\u003eWhat won\u0027t people do in the name of\nfashion, right?",
  "Com_Talk_04": "\u003csp:3:0:2:0001\u003e\u003csnd:Sad\u003eNo? That\u0027s a shame.",
  "Talk1028b_02": "\u003csp:3:0:2:0700\u003eThe Hylians are pretty incredible to have\nbuilt something so impressive.",
  "Talk1003": "\u003csp:3:0:2:0100\u003e\u003csnd:Greeting\u003eHey there!\u003csp:5:0:0\u003e Thanks for your business!",
  "Com_Talk_05": "\u003csp:3:0:2:0000\u003eI\u0027ll buy anything!",
  "Talk1028b_03": "\u003csp:3:0:2:0000\u003e\u003csnd:Happy\u003eWhat were they calling it? A \u003cclr:0000\u003eSkyview\nTower \u003cclr:ffff\u003eor something?\u003csp:0:4:0\u003eIt\u0027s still dark right now, but when it\u0027s\nturned on, they say it\u0027ll light up the sky\npretty far out.\u003csp:5:1:0\u003e\n\u003csp:3:0:2:0701\u003eI doubt it\u0027ll warm you up like a \u003cclr:0000\u003ebonfire\u003cclr:ffff\u003e,\nbut it\u0027ll be hard to beat it for size and\nsheer brightness.\u003csp:0:4:0\u003ePretty soon, my \u003cclr:0000\u003ebonfires \u003cclr:ffff\u003ewon\u0027t be quite\nthe landmark they are now.",
  "Talk1028b_04": "\u003csp:3:0:2:0400\u003e\u003csnd:TalkPositive\u003eThe Hylians are pretty incredible to have\nbuilt something so impressive.",
  "Talk1005": "\u003csp:3:0:2:0000\u003e\u003csnd:Greeting\u003eHey, thanks for coming out so late!\u003cclr:0000\u003e\u003csp:0:4:0\u003eBrazen Beak \u003cclr:ffff\u003eis open 24 hours.\nStop by whenever!",
  "Talk1006": "\u003csp:3:0:2:0001\u003e\u003csnd:TalkPositive\u003eSo then, what can I do for you today?",
  "Talk1007": "\u003csp:3:0:2:0001\u003e\u003csnd:TalkPositive\u003eThanks for stopping by!",
  "Com_Talk_33": "\u003csp:3:0:2:0000\u003eJust one? Then I can give you\n\u003cclr:0000\u003e\u003csp:2:12:2c:2600530068006f0070005f00540072006100640065004900740065006d0050007200690063006500ffff00cd\u003e \u003csp:c9:6:1c:0a00720075007000650065000c007200750070006500650073000000\u003e \u003cclr:ffff\u003efor it.",
  "Talk1008": "\u003csp:3:0:2:0001\u003e\u003csnd:TalkPositive\u003eOK. Hope to see you again!",
  "Near10": "That works as a landmark.",
  "Talk1009": "\u003csp:3:0:2:0001\u003e\u003csnd:TalkPositive\u003eNow then, what else can I do for you?",
  "Com_Talk_35": "\u003csp:3:0:2:0401\u003eAll \u003csp:2:f:28:2200530068006f0070005f00540072006100640065004900740065006d004e0075006d00ffff00cd\u003e of them? For that, I could give\nyou \u003cclr:0000\u003e\u003csp:2:12:2c:2600530068006f0070005f00540072006100640065004900740065006d0050007200690063006500ffff00cd\u003e \u003csp:c9:6:1c:0a00720075007000650065000c007200750070006500650073000000\u003e\u003cclr:ffff\u003e.",
  "5500": "Sure, yeah!",
  "Talk1029b": "\u003csp:3:0:2:0500\u003e\u003csnd:QuestionNormal\u003eAlthough... Let\u0027s be honest—the \u003cclr:0000\u003eSkyview\nTower \u003cclr:ffff\u003eis much easier to spot with all the\nlights set up around it.",
  "5501": "Maybe next time.",
  "5503": "Never mind.",
  "Talk2001": "\u003csp:3:0:2:0000\u003e\u003csnd:Happy_00\u003eWhen the blizzard drove off most of the\nadults, the kids hung in there and kept\nthings going. That includes the shops.\u003csp:0:4:0\u003e\u003csp:3:0:2:0101\u003eI can\u0027t express enough how much we owe\nthe little ones. They\u0027re the saviors of\nthis village.",
  "Com_Talk_02b": "\u003csp:3:0:2:0100\u003e\u003csnd:LaughS\u003eThanks for your business! So...is that it?\nYou don\u0027t want to sell anything else?"
}