{
  "Talk_0005": "\u003csp:3:0:2:0700\u003eLady Impa... What would you say to a\ntargeted approach? Instead of looking\neverywhere, we start by finding a clue.",
  "Talk_0006": "\u003csp:3:0:2:0c00\u003e\u003csnd:Trouble_00\u003eHmm. The \u003cclr:0000\u003eForgotten Temple \u003cclr:ffff\u003ewould be\nbest for that, I suppose.\n\nIt\u0027s in \u003cclr:0000\u003ea canyon in Hebra\u003cclr:ffff\u003e. We can only\nhope it is not too dangerous there.",
  "Near_0001": "The other geoglyphs...",
  "Talk_0007": "\u003csp:3:0:2:0700\u003eFor now, let us continue combing the land\nfor information. We need every scrap of\nevidence we can find.",
  "Talk_0001": "\u003csp:3:0:2:0700\u003eSo... Have you learned of any new\n\u003cclr:0000\u003egeoglyph \u003cclr:ffff\u003elocations?",
  "Talk_0008": "\u003csp:3:0:2:0700\u003eThank you.",
  "Talk_0010": "And, Sir Link, we could use your help\nas well. Please continue to search\nfor geoglyphs.\nOr you could go to that \u003cclr:0000\u003eForgotten Temple\u003cclr:ffff\u003e\nat the bottom of \u003cclr:0000\u003ea canyon in Hebra\u003cclr:ffff\u003e.",
  "Talk_0002": "\u003csp:3:0:2:0700\u003e\u003csnd:Sad_00\u003eWe have balloons scouring the kingdom\nfor them, although it\u0027s hardly quick work.\n\nMaybe we could survey more territory by\nlaunching out of the Skyview Towers...\u003csp:5:0:0\u003e\nbut no, that\u0027s not safe.",
  "Talk_0009": "\u003csp:3:0:2:0000\u003e\u003csnd:Happy_00\u003eThe survey team will support you however\nwe can. Many hands, as they say!",
  "Talk_0003": "\u003csp:3:0:2:0700\u003e\u003csnd:SurpriseS_00\u003eHm? Oh, it\u0027s you, Link.",
  "Talk_0004": "\u003csp:3:0:2:0c00\u003e\u003csnd:Trouble_01\u003eWe are searching in every region for\ngeoglyphs. Alas, they are not as easy to\nfind as one might expect."
}